sdg_utils/__init__.py
sdg_utils/log.py
sdg_utils/terminal.py
sdg_utils/terminal_utils.py
sdg_utils/test.py
sdg_utils-1.5.dist-info/LICENSE
sdg_utils-1.5.dist-info/METADATA
sdg_utils-1.5.dist-info/WHEEL
sdg_utils-1.5.dist-info/top_level.txt
sdg_utils-1.5.dist-info/RECORD
