Metadata-Version: 2.1
Name: sdg-utils
Version: 1.5
Summary: sdg utils
Author: chernecov_ev
Author-email: chernecov.ev@gmail.com
Classifier: Programming Language :: Python :: 3
Classifier: License :: OSI Approved :: MIT License
Classifier: Operating System :: OS Independent
Requires-Python: >=3.4
License-File: LICENSE
Requires-Dist: wheel
Requires-Dist: colorama
Requires-Dist: pyserial
